perplexity_webui_scraper/__init__.py
perplexity_webui_scraper/cli/get_perplexity_session_token.py
perplexity_webui_scraper/config.py
perplexity_webui_scraper/constants.py
perplexity_webui_scraper/core.py
perplexity_webui_scraper/enums.py
perplexity_webui_scraper/exceptions.py
perplexity_webui_scraper/http.py
perplexity_webui_scraper/limits.py
perplexity_webui_scraper/logging.py
perplexity_webui_scraper/mcp/__init__.py
perplexity_webui_scraper/mcp/__main__.py
perplexity_webui_scraper/mcp/server.py
perplexity_webui_scraper/models.py
perplexity_webui_scraper/py.typed
perplexity_webui_scraper/resilience.py
perplexity_webui_scraper/types.py
perplexity_webui_scraper-0.4.0.dist-info/WHEEL
perplexity_webui_scraper-0.4.0.dist-info/entry_points.txt
perplexity_webui_scraper-0.4.0.dist-info/METADATA
perplexity_webui_scraper-0.4.0.dist-info/RECORD
