Metadata-Version: 2.4
Name: perplexity-webui-scraper
Version: 0.4.0
Summary: Python scraper to extract AI responses from Perplexity's web interface.
Keywords: perplexity,ai,scraper,webui,api,client
Author: henrique-coder
Author-email: henrique-coder <henriquemoreira10fk@gmail.com>
License-Expression: MIT
Classifier: Development Status :: 4 - Beta
Classifier: Intended Audience :: Developers
Classifier: License :: OSI Approved :: MIT License
Classifier: Operating System :: OS Independent
Classifier: Programming Language :: Python :: 3
Classifier: Programming Language :: Python :: 3.10
Classifier: Programming Language :: Python :: 3.11
Classifier: Programming Language :: Python :: 3.12
Classifier: Programming Language :: Python :: 3.13
Classifier: Programming Language :: Python :: 3.14
Classifier: Topic :: Internet :: WWW/HTTP
Classifier: Topic :: Software Development :: Libraries :: Python Modules
Classifier: Typing :: Typed
Requires-Dist: curl-cffi>=0.14.0
Requires-Dist: loguru>=0.7.3
Requires-Dist: orjson>=3.11.6
Requires-Dist: pydantic>=2.12.5
Requires-Dist: tenacity>=9.1.2
Requires-Dist: fastmcp>=2.14.4 ; extra == 'mcp'
Requires-Python: >=3.10, <3.15
Project-URL: Homepage, https://github.com/henrique-coder/perplexity-webui-scraper
Project-URL: Documentation, https://github.com/henrique-coder/perplexity-webui-scraper#readme
Project-URL: Repository, https://github.com/henrique-coder/perplexity-webui-scraper.git
Project-URL: Issues, https://github.com/henrique-coder/perplexity-webui-scraper/issues
Project-URL: Changelog, https://github.com/henrique-coder/perplexity-webui-scraper/releases
Provides-Extra: mcp
